browse/__init__.py
browse/browser_engine.py
browse/cli.py
browse/observation_processor.py
browse/server.py
browse/utils.py
browse_cli-0.1.1.dist-info/METADATA
browse_cli-0.1.1.dist-info/WHEEL
browse_cli-0.1.1.dist-info/entry_points.txt
browse_cli-0.1.1.dist-info/top_level.txt
browse_cli-0.1.1.dist-info/RECORD
