Metadata-Version: 2.1
Name: browse-cli
Version: 0.1.1
Summary: A simple CLI tool to browse the web
Author-email: Govind Pimpale <gpimpale29@gmail.com>
License: MIT
Project-URL: Homepage, https://github.com/pimpale/browse-cli
Requires-Dist: click
Requires-Dist: playwright
